{"prodota_id": 345, "pdmafia_id": 297, "name": "DigenShip Mafia №345 - Боруто сын Наруто, внук Минато", "setting_name": "Наруто", "host": "OMGVERYLONGNAME", "time_str": "2017-10-28 19:53:00", "day_count": "6 дней", "tags": ["Мирный город"], "faction_winner_list": ["norole", "active"], "player_list": [{"name": "Avrilka", "role_name": "Темари", "status": {"exit_day_number": "5", "exit_reason": "Убит мафией", "exit_frame": "Ночь"}}, {"name": "Gram4eg", "role_name": "Хината Хьюга", "status": {"exit_day_number": "5", "exit_reason": "Убит мафией", "exit_frame": "Ночь"}}, {"name": "Никитка)))", "role_name": "Сай", "status": {"exit_day_number": "3", "exit_reason": "Убит мафией", "exit_frame": "Ночь"}}, {"name": "Hikara", "role_name": "Шикамару Нара", "status": {"exit_day_number": "2", "exit_reason": "Убит мафией", "exit_frame": "Ночь"}}, {"name": "Baza_KAiF", "role_name": "Яманака Ино", "status": {"exit_day_number": "2", "exit_reason": "Убит мафией", "exit_frame": "Ночь"}}, {"name": "Fint", "role_name": "Карин", "status": {"exit_day_number": "6", "exit_reason": "Убит мафией", "exit_frame": "Ночь"}}, {"name": "toouur", "role_name": "Суйгетцу", "status": {"exit_day_number": "6", "exit_reason": "Выгнан", "exit_frame": "День"}}, {"name": "Whats_Up4you", "role_name": "Учиха Итачи", "status": {"exit_day_number": "5", "exit_reason": "Выгнан", "exit_frame": "День"}}, {"name": "ZombBomb", "role_name": "Зэтцу", "status": {"exit_day_number": "4", "exit_reason": "Выгнан", "exit_frame": "День"}}, {"name": "pnanrkotikivj", "role_name": "Джуго", "status": {"exit_day_number": "3", "exit_reason": "Убит активом", "exit_frame": "День"}}, {"name": "Fulelgupport", "role_name": "Кабуто", "status": {"exit_day_number": "2", "exit_reason": "Выгнан", "exit_frame": "День"}}, {"name": "TheEndlessStory", "role_name": "Киллер Би", "status": {"exit_day_number": "2", "exit_reason": "Умер", "exit_frame": "День"}}, {"name": "ЖУМОНГ", "role_name": "Манда", "status": {"exit_day_number": "3", "exit_reason": "Выгнан", "exit_frame": "День"}}, {"name": "aac", "role_name": "Мирный житель", "status": {"exit_day_number": "3", "exit_reason": "Убит мафией", "exit_frame": "Ночь"}}, {"name": "Cryless", "role_name": "Мирный житель", "status": {"exit_day_number": "2", "exit_reason": "Убит мафией", "exit_frame": "Ночь"}}, {"name": "chopchop1", "role_name": "Мирный житель", "status": {"exit_day_number": "2", "exit_reason": "Убит мафией", "exit_frame": "Ночь"}}, {"name": "wisp74rus", "role_name": "Мирный житель", "status": {"exit_day_number": "1", "exit_reason": "Убит мафией", "exit_frame": "Ночь"}}]}