{"prodota_id": 173, "pdmafia_id": 114, "name": "Мафия №173 - Тайга", "setting_name": "Тайга", "host": "TheDeadSkin", "time_str": "2013-05-27 15:21:00", "day_count": "4 дней", "tags": ["Мирный город"], "faction_winner_list": ["norole", "active"], "player_list": [{"name": "MeganFox", "role_name": "Александр Крылов", "status": {"exit_day_number": "3", "exit_reason": "Молния", "exit_frame": "День"}}, {"name": "JUWS", "role_name": "Николай Быков", "status": {"exit_day_number": "2", "exit_reason": "Убит активом", "exit_frame": "Ночь"}}, {"name": "Lionell", "role_name": "Кулькидия", "status": {"exit_day_number": "4", "exit_reason": "Умер", "exit_frame": "Ночь"}}, {"name": "NaniQue-", "role_name": "Здоровяк", "status": {"exit_day_number": "3", "exit_reason": "Убит активом", "exit_frame": "Ночь"}}, {"name": "VovaZbest", "role_name": "Кремос", "status": {"exit_day_number": "2", "exit_reason": "Молния", "exit_frame": "День"}}, {"name": "D1ggee", "role_name": "Завербованный", "status": {"exit_day_number": "2", "exit_reason": "Выгнан", "exit_frame": "День"}}, {"name": "R0ss0ha", "role_name": "Богдан Шевченко", "status": {"exit_day_number": "4", "exit_reason": "Выгнан", "exit_frame": "День"}}, {"name": "MANAFEST", "role_name": "Мирный житель", "status": {"exit_day_number": "3", "exit_reason": "Выгнан", "exit_frame": "День"}}, {"name": "Verhein", "role_name": "Мирный житель", "status": {"exit_day_number": "2", "exit_reason": "Убит маньяком", "exit_frame": "Ночь"}}, {"name": "alexinus", "role_name": "Мирный житель", "status": {"exit_day_number": "2", "exit_reason": "Молния", "exit_frame": "День"}}, {"name": "otarik", "role_name": "Мирный житель", "status": {"exit_day_number": "1", "exit_reason": "Убит мафией", "exit_frame": "Ночь"}}, {"name": "Джамал", "role_name": "Мирный житель", "status": {"exit_day_number": "1", "exit_reason": "Выгнан", "exit_frame": "День"}}]}