{"prodota_id": 71, "pdmafia_id": 10, "name": "Мафия # 71: Гарри поттер v 2.0", "setting_name": "Гарри поттер v 2.0", "host": "Mizakylt", "time_str": "2012-01-17 13:48:00", "day_count": "6 дней", "tags": ["Мирный город"], "faction_winner_list": ["norole", "active"], "player_list": [{"name": "Waro", "role_name": "Минерва Макгоногал", "status": {"exit_day_number": "5", "exit_reason": "Убит мафией", "exit_frame": "Ночь"}}, {"name": "Fiend.Jackson", "role_name": "Северус Снегг", "status": {"exit_day_number": "4", "exit_reason": "Убит маньяком", "exit_frame": "Ночь"}}, {"name": "Seprit", "role_name": "Рон Уизли", "status": {"exit_day_number": "4", "exit_reason": "Убит мафией", "exit_frame": "День"}}, {"name": "Freagent", "role_name": "Артур Уизли", "status": {"exit_day_number": "3", "exit_reason": "Убит мафией", "exit_frame": "Ночь"}}, {"name": "OKPOLLIKA", "role_name": "Беллатрисса Лейнстрейдж", "status": {"exit_day_number": "6", "exit_reason": "Выгнан", "exit_frame": "День"}}, {"name": "XaBK", "role_name": "Драко Малфой", "status": {"exit_day_number": "4", "exit_reason": "Выгнан", "exit_frame": "День"}}, {"name": "Dude)", "role_name": "Люциус Малфой", "status": {"exit_day_number": "3", "exit_reason": "Убит маньяком", "exit_frame": "Ночь"}}, {"name": "IceEyes", "role_name": "Питер Петтигрю", "status": {"exit_day_number": "3", "exit_reason": "Умер в клетке", "exit_frame": "День"}}, {"name": "Semenuch", "role_name": "Волан Де Морт", "status": {"exit_day_number": "3", "exit_reason": "Выгнан", "exit_frame": "День"}}, {"name": "Zavarka", "role_name": "Василиск", "status": {"exit_day_number": "2", "exit_reason": "Выгнан", "exit_frame": "День"}}, {"name": "Fenfir", "role_name": "Озверевший Дементор", "status": {"exit_day_number": "5", "exit_reason": "Выгнан", "exit_frame": "День"}}, {"name": "RedBedHorse", "role_name": "Мирный житель", "status": {"exit_day_number": "5", "exit_reason": "Молния", "exit_frame": "День"}}, {"name": "MeganFox", "role_name": "Мирный житель", "status": {"exit_day_number": "5", "exit_reason": "Умер в клетке", "exit_frame": "День"}}, {"name": "st1gma", "role_name": "Мирный житель", "status": {"exit_day_number": "4", "exit_reason": "Убит мафией", "exit_frame": "Ночь"}}, {"name": "NaniQue-", "role_name": "Мирный житель", "status": {"exit_day_number": "4", "exit_reason": "Убит мафией", "exit_frame": "День"}}, {"name": "Marina_oR1ver", "role_name": "Мирный житель", "status": {"exit_day_number": "4", "exit_reason": "Убит мафией", "exit_frame": "День"}}, {"name": "insto", "role_name": "Мирный житель", "status": {"exit_day_number": "3", "exit_reason": "Убит мафией", "exit_frame": "День"}}, {"name": "KostaXX", "role_name": "Мирный житель", "status": {"exit_day_number": "2", "exit_reason": "Убит активом", "exit_frame": "Ночь"}}, {"name": "Murr", "role_name": "Мирный житель", "status": {"exit_day_number": "2", "exit_reason": "Убит мафией", "exit_frame": "Ночь"}}, {"name": "godfrey", "role_name": "Мирный житель", "status": {"exit_day_number": "2", "exit_reason": "Умер в клетке", "exit_frame": "День"}}, {"name": "o_Oiser", "role_name": "Мирный житель", "status": {"exit_day_number": "1", "exit_reason": "Убит маньяком", "exit_frame": "Ночь"}}, {"name": "JustJeka", "role_name": "Мирный житель", "status": {"exit_day_number": "1", "exit_reason": "Выгнан", "exit_frame": "День"}}, {"name": "alexinus", "role_name": "Мирный житель", "status": {"exit_day_number": "1", "exit_reason": "Молния", "exit_frame": "День"}}]}